{
  "run": {
    "javaVersion": "17",
    "scenario": "1",
    "startTime": "2026-03-02T14:16:30.165Z",
    "endTime": "2026-03-02T14:30:31.387Z",
    "albUrl": "http://java-bench-alb-832402291.us-east-1.elb.amazonaws.com",
    "jvm": {
      "settings": "-XX:+UseG1GC -Xmx1024m"
    }
  },
  "k6": {
    "durationSeconds": 841.222,
    "totalRequests": 64517,
    "throughputRps": 76.685807,
    "errorRatePercent": 0,
    "errorCount": 0,
    "errorCountTotal": 64517
  },
  "containerAws": {
    "periodSeconds": 60,
    "CpuUtilized": {
      "Average": {
        "summary": {
          "min": 12.405528564453125,
          "max": 511.97462239583336,
          "avg": 307.45463521321614,
          "count": 14
        },
        "datapoints": [
          {
            "timestamp": "2026-03-02T14:16:00.000Z",
            "value": 12.405528564453125,
            "unit": "None"
          },
          {
            "timestamp": "2026-03-02T14:17:00.000Z",
            "value": 36.75474690755208,
            "unit": "None"
          },
          {
            "timestamp": "2026-03-02T14:18:00.000Z",
            "value": 72.64040690104167,
            "unit": "None"
          },
          {
            "timestamp": "2026-03-02T14:19:00.000Z",
            "value": 107.52910481770834,
            "unit": "None"
          },
          {
            "timestamp": "2026-03-02T14:20:00.000Z",
            "value": 211.26227376302083,
            "unit": "None"
          },
          {
            "timestamp": "2026-03-02T14:21:00.000Z",
            "value": 227.20248697916668,
            "unit": "None"
          },
          {
            "timestamp": "2026-03-02T14:22:00.000Z",
            "value": 295.69903645833335,
            "unit": "None"
          },
          {
            "timestamp": "2026-03-02T14:23:00.000Z",
            "value": 398.1727994791667,
            "unit": "None"
          },
          {
            "timestamp": "2026-03-02T14:24:00.000Z",
            "value": 511.84826822916665,
            "unit": "None"
          },
          {
            "timestamp": "2026-03-02T14:25:00.000Z",
            "value": 511.8704557291667,
            "unit": "None"
          },
          {
            "timestamp": "2026-03-02T14:26:00.000Z",
            "value": 383.72737630208337,
            "unit": "None"
          },
          {
            "timestamp": "2026-03-02T14:27:00.000Z",
            "value": 511.97462239583336,
            "unit": "None"
          },
          {
            "timestamp": "2026-03-02T14:28:00.000Z",
            "value": 511.66854166666667,
            "unit": "None"
          },
          {
            "timestamp": "2026-03-02T14:29:00.000Z",
            "value": 511.6092447916667,
            "unit": "None"
          }
        ]
      },
      "Maximum": {
        "summary": {
          "min": 12.405528564453125,
          "max": 511.97462239583336,
          "avg": 319.78098461332775,
          "count": 14
        },
        "datapoints": [
          {
            "timestamp": "2026-03-02T14:16:00.000Z",
            "value": 12.405528564453125,
            "unit": "None"
          },
          {
            "timestamp": "2026-03-02T14:17:00.000Z",
            "value": 36.75474690755208,
            "unit": "None"
          },
          {
            "timestamp": "2026-03-02T14:18:00.000Z",
            "value": 72.64040690104167,
            "unit": "None"
          },
          {
            "timestamp": "2026-03-02T14:19:00.000Z",
            "value": 107.52910481770834,
            "unit": "None"
          },
          {
            "timestamp": "2026-03-02T14:20:00.000Z",
            "value": 256,
            "unit": "None"
          },
          {
            "timestamp": "2026-03-02T14:21:00.000Z",
            "value": 227.20248697916668,
            "unit": "None"
          },
          {
            "timestamp": "2026-03-02T14:22:00.000Z",
            "value": 295.69903645833335,
            "unit": "None"
          },
          {
            "timestamp": "2026-03-02T14:23:00.000Z",
            "value": 398.1727994791667,
            "unit": "None"
          },
          {
            "timestamp": "2026-03-02T14:24:00.000Z",
            "value": 511.84826822916665,
            "unit": "None"
          },
          {
            "timestamp": "2026-03-02T14:25:00.000Z",
            "value": 511.8704557291667,
            "unit": "None"
          },
          {
            "timestamp": "2026-03-02T14:26:00.000Z",
            "value": 511.5585416666667,
            "unit": "None"
          },
          {
            "timestamp": "2026-03-02T14:27:00.000Z",
            "value": 511.97462239583336,
            "unit": "None"
          },
          {
            "timestamp": "2026-03-02T14:28:00.000Z",
            "value": 511.66854166666667,
            "unit": "None"
          },
          {
            "timestamp": "2026-03-02T14:29:00.000Z",
            "value": 511.6092447916667,
            "unit": "None"
          }
        ]
      }
    },
    "MemoryUtilized": {
      "Average": {
        "summary": {
          "min": 547,
          "max": 1220,
          "avg": 1019.4642857142857,
          "count": 14
        },
        "datapoints": [
          {
            "timestamp": "2026-03-02T14:16:00.000Z",
            "value": 1069,
            "unit": "Megabytes"
          },
          {
            "timestamp": "2026-03-02T14:17:00.000Z",
            "value": 1070,
            "unit": "Megabytes"
          },
          {
            "timestamp": "2026-03-02T14:18:00.000Z",
            "value": 1070,
            "unit": "Megabytes"
          },
          {
            "timestamp": "2026-03-02T14:19:00.000Z",
            "value": 1070,
            "unit": "Megabytes"
          },
          {
            "timestamp": "2026-03-02T14:20:00.000Z",
            "value": 547,
            "unit": "Megabytes"
          },
          {
            "timestamp": "2026-03-02T14:21:00.000Z",
            "value": 1070,
            "unit": "Megabytes"
          },
          {
            "timestamp": "2026-03-02T14:22:00.000Z",
            "value": 1071,
            "unit": "Megabytes"
          },
          {
            "timestamp": "2026-03-02T14:23:00.000Z",
            "value": 1071,
            "unit": "Megabytes"
          },
          {
            "timestamp": "2026-03-02T14:24:00.000Z",
            "value": 1129,
            "unit": "Megabytes"
          },
          {
            "timestamp": "2026-03-02T14:25:00.000Z",
            "value": 1220,
            "unit": "Megabytes"
          },
          {
            "timestamp": "2026-03-02T14:26:00.000Z",
            "value": 643.5,
            "unit": "Megabytes"
          },
          {
            "timestamp": "2026-03-02T14:27:00.000Z",
            "value": 1051,
            "unit": "Megabytes"
          },
          {
            "timestamp": "2026-03-02T14:28:00.000Z",
            "value": 1042,
            "unit": "Megabytes"
          },
          {
            "timestamp": "2026-03-02T14:29:00.000Z",
            "value": 1149,
            "unit": "Megabytes"
          }
        ]
      },
      "Maximum": {
        "summary": {
          "min": 1042,
          "max": 1239,
          "avg": 1099.357142857143,
          "count": 14
        },
        "datapoints": [
          {
            "timestamp": "2026-03-02T14:16:00.000Z",
            "value": 1069,
            "unit": "Megabytes"
          },
          {
            "timestamp": "2026-03-02T14:17:00.000Z",
            "value": 1070,
            "unit": "Megabytes"
          },
          {
            "timestamp": "2026-03-02T14:18:00.000Z",
            "value": 1070,
            "unit": "Megabytes"
          },
          {
            "timestamp": "2026-03-02T14:19:00.000Z",
            "value": 1070,
            "unit": "Megabytes"
          },
          {
            "timestamp": "2026-03-02T14:20:00.000Z",
            "value": 1070,
            "unit": "Megabytes"
          },
          {
            "timestamp": "2026-03-02T14:21:00.000Z",
            "value": 1070,
            "unit": "Megabytes"
          },
          {
            "timestamp": "2026-03-02T14:22:00.000Z",
            "value": 1071,
            "unit": "Megabytes"
          },
          {
            "timestamp": "2026-03-02T14:23:00.000Z",
            "value": 1071,
            "unit": "Megabytes"
          },
          {
            "timestamp": "2026-03-02T14:24:00.000Z",
            "value": 1129,
            "unit": "Megabytes"
          },
          {
            "timestamp": "2026-03-02T14:25:00.000Z",
            "value": 1220,
            "unit": "Megabytes"
          },
          {
            "timestamp": "2026-03-02T14:26:00.000Z",
            "value": 1239,
            "unit": "Megabytes"
          },
          {
            "timestamp": "2026-03-02T14:27:00.000Z",
            "value": 1051,
            "unit": "Megabytes"
          },
          {
            "timestamp": "2026-03-02T14:28:00.000Z",
            "value": 1042,
            "unit": "Megabytes"
          },
          {
            "timestamp": "2026-03-02T14:29:00.000Z",
            "value": 1149,
            "unit": "Megabytes"
          }
        ]
      }
    },
    "NetworkRxBytes": {
      "Sum": {
        "summary": {
          "min": 171063,
          "max": 9038333,
          "avg": 4578020.571428572,
          "count": 14
        },
        "datapoints": [
          {
            "timestamp": "2026-03-02T14:16:00.000Z",
            "value": 171063,
            "unit": "Bytes/Second"
          },
          {
            "timestamp": "2026-03-02T14:17:00.000Z",
            "value": 620429,
            "unit": "Bytes/Second"
          },
          {
            "timestamp": "2026-03-02T14:18:00.000Z",
            "value": 1364283,
            "unit": "Bytes/Second"
          },
          {
            "timestamp": "2026-03-02T14:19:00.000Z",
            "value": 2442370,
            "unit": "Bytes/Second"
          },
          {
            "timestamp": "2026-03-02T14:20:00.000Z",
            "value": 4090262,
            "unit": "Bytes/Second"
          },
          {
            "timestamp": "2026-03-02T14:21:00.000Z",
            "value": 5575180,
            "unit": "Bytes/Second"
          },
          {
            "timestamp": "2026-03-02T14:22:00.000Z",
            "value": 7238955,
            "unit": "Bytes/Second"
          },
          {
            "timestamp": "2026-03-02T14:23:00.000Z",
            "value": 9038333,
            "unit": "Bytes/Second"
          },
          {
            "timestamp": "2026-03-02T14:24:00.000Z",
            "value": 6414580,
            "unit": "Bytes/Second"
          },
          {
            "timestamp": "2026-03-02T14:25:00.000Z",
            "value": 5584492,
            "unit": "Bytes/Second"
          },
          {
            "timestamp": "2026-03-02T14:26:00.000Z",
            "value": 5416018,
            "unit": "Bytes/Second"
          },
          {
            "timestamp": "2026-03-02T14:27:00.000Z",
            "value": 5441956,
            "unit": "Bytes/Second"
          },
          {
            "timestamp": "2026-03-02T14:28:00.000Z",
            "value": 5318334,
            "unit": "Bytes/Second"
          },
          {
            "timestamp": "2026-03-02T14:29:00.000Z",
            "value": 5376033,
            "unit": "Bytes/Second"
          }
        ]
      }
    },
    "NetworkTxBytes": {
      "Sum": {
        "summary": {
          "min": 339677,
          "max": 13512203,
          "avg": 6900086.142857143,
          "count": 14
        },
        "datapoints": [
          {
            "timestamp": "2026-03-02T14:16:00.000Z",
            "value": 339677,
            "unit": "Bytes/Second"
          },
          {
            "timestamp": "2026-03-02T14:17:00.000Z",
            "value": 1024664,
            "unit": "Bytes/Second"
          },
          {
            "timestamp": "2026-03-02T14:18:00.000Z",
            "value": 2129324,
            "unit": "Bytes/Second"
          },
          {
            "timestamp": "2026-03-02T14:19:00.000Z",
            "value": 3745058,
            "unit": "Bytes/Second"
          },
          {
            "timestamp": "2026-03-02T14:20:00.000Z",
            "value": 6178237,
            "unit": "Bytes/Second"
          },
          {
            "timestamp": "2026-03-02T14:21:00.000Z",
            "value": 8438917,
            "unit": "Bytes/Second"
          },
          {
            "timestamp": "2026-03-02T14:22:00.000Z",
            "value": 10849193,
            "unit": "Bytes/Second"
          },
          {
            "timestamp": "2026-03-02T14:23:00.000Z",
            "value": 13512203,
            "unit": "Bytes/Second"
          },
          {
            "timestamp": "2026-03-02T14:24:00.000Z",
            "value": 9554066,
            "unit": "Bytes/Second"
          },
          {
            "timestamp": "2026-03-02T14:25:00.000Z",
            "value": 8461858,
            "unit": "Bytes/Second"
          },
          {
            "timestamp": "2026-03-02T14:26:00.000Z",
            "value": 8108490,
            "unit": "Bytes/Second"
          },
          {
            "timestamp": "2026-03-02T14:27:00.000Z",
            "value": 8230401,
            "unit": "Bytes/Second"
          },
          {
            "timestamp": "2026-03-02T14:28:00.000Z",
            "value": 7880949,
            "unit": "Bytes/Second"
          },
          {
            "timestamp": "2026-03-02T14:29:00.000Z",
            "value": 8148169,
            "unit": "Bytes/Second"
          }
        ]
      }
    }
  },
  "prometheus": {
    "metrics": {
      "heap-used-bytes": {
        "summary": null,
        "seriesCount": 0
      },
      "non-heap-used-bytes": {
        "summary": null,
        "seriesCount": 0
      },
      "gc-pause-rate-5m": {
        "summary": null,
        "seriesCount": 0
      },
      "gc-pause-max": {
        "summary": null,
        "seriesCount": 0
      },
      "live-threads": {
        "summary": null,
        "seriesCount": 0
      },
      "process-cpu-usage": {
        "summary": null,
        "seriesCount": 0
      },
      "system-cpu-usage": {
        "summary": null,
        "seriesCount": 0
      },
      "heap-committed-bytes": {
        "summary": null,
        "seriesCount": 0
      },
      "classes-loaded": {
        "summary": null,
        "seriesCount": 0
      },
      "gc-count-rate-5m": {
        "summary": null,
        "seriesCount": 0
      }
    },
    "labels": {}
  },
  "ecs": {
    "clusterName": "java-bench-cluster",
    "serviceName": "java-bench-service",
    "desiredCount": 1,
    "runningCount": 1,
    "taskDefinitionArn": "arn:aws:ecs:us-east-1:913846010507:task-definition/java-bench-task:84",
    "taskCpu": "512",
    "taskMemory": "2048",
    "containers": [
      {
        "name": "java-bench-app",
        "image": "913846010507.dkr.ecr.us-east-1.amazonaws.com/benchmark-app:rest-java17-1-2026-02-27-1",
        "cpu": 512,
        "memory": 2048,
        "memoryReservation": null,
        "portMappings": [
          {
            "containerPort": 8080,
            "hostPort": 8080,
            "protocol": "tcp"
          }
        ],
        "logConfiguration": {
          "logDriver": "awslogs",
          "options": {
            "awslogs-group": "/ecs/java-bench-app",
            "awslogs-create-group": "true",
            "awslogs-region": "us-east-1",
            "awslogs-stream-prefix": "ecs"
          }
        },
        "healthCheck": {
          "command": [
            "CMD-SHELL",
            "curl -f http://localhost:8080/actuator/health || exit 1"
          ],
          "interval": 30,
          "timeout": 10,
          "retries": 3,
          "startPeriod": 120
        },
        "environment": [
          {
            "name": "METRICS_CLOUDWATCH_ENABLED",
            "value": "true"
          },
          {
            "name": "METRICS_CLOUDWATCH_NAMESPACE",
            "value": "JavaBenchmark"
          },
          {
            "name": "AWS_REGION",
            "value": "us-east-1"
          },
          {
            "name": "SPRING_DATASOURCE_URL",
            "value": "jdbc:postgresql://localhost:5432/benchmarkdb"
          },
          {
            "name": "SPRING_DATASOURCE_PASSWORD",
            "value": "BenchUserStrongPass123!"
          },
          {
            "name": "SPRING_PROFILES_ACTIVE",
            "value": "ecs"
          },
          {
            "name": "DB_POOL_SIZE",
            "value": "20"
          },
          {
            "name": "SPRING_DATASOURCE_USERNAME",
            "value": "benchuser"
          },
          {
            "name": "APP_IMAGE",
            "value": "913846010507.dkr.ecr.us-east-1.amazonaws.com/benchmark-app:rest-java17-1-2026-02-27-1"
          },
          {
            "name": "METRICS_CLOUDWATCH_STEP",
            "value": "1m"
          },
          {
            "name": "JAVA_VERSION",
            "value": "17"
          },
          {
            "name": "VIRTUAL_THREADS_ENABLED",
            "value": "false"
          }
        ]
      }
    ]
  },
  "rds": {
    "instanceId": "java-bench-db",
    "instanceClass": "db.t4g.micro",
    "engine": "postgres",
    "engineVersion": "17.6",
    "allocatedStorage": 20,
    "status": "available",
    "masterUsername": "benchuser",
    "databaseName": "benchmarkdb",
    "port": 5432,
    "multiAZ": false,
    "backupRetentionPeriod": 0,
    "preferredBackupWindow": "05:49-06:19",
    "preferredMaintenanceWindow": "thu:10:11-thu:10:41",
    "maxAllocatedStorage": null
  },
  "rdsAws": {
    "periodSeconds": 60,
    "CPUUtilization": {
      "Average": {
        "summary": {
          "min": 7.350612551045922,
          "max": 74.88281315161727,
          "avg": 41.32358728889893,
          "count": 14
        },
        "datapoints": [
          {
            "timestamp": "2026-03-02T14:16:00.000Z",
            "value": 7.350612551045922,
            "unit": "Percent"
          },
          {
            "timestamp": "2026-03-02T14:17:00.000Z",
            "value": 11.341666666666667,
            "unit": "Percent"
          },
          {
            "timestamp": "2026-03-02T14:18:00.000Z",
            "value": 16.35806069898835,
            "unit": "Percent"
          },
          {
            "timestamp": "2026-03-02T14:19:00.000Z",
            "value": 26.716029617770666,
            "unit": "Percent"
          },
          {
            "timestamp": "2026-03-02T14:20:00.000Z",
            "value": 39.56666666666667,
            "unit": "Percent"
          },
          {
            "timestamp": "2026-03-02T14:21:00.000Z",
            "value": 51.60317301603173,
            "unit": "Percent"
          },
          {
            "timestamp": "2026-03-02T14:22:00.000Z",
            "value": 65.2572151814412,
            "unit": "Percent"
          },
          {
            "timestamp": "2026-03-02T14:23:00.000Z",
            "value": 74.88281315161727,
            "unit": "Percent"
          },
          {
            "timestamp": "2026-03-02T14:24:00.000Z",
            "value": 52.017922281259885,
            "unit": "Percent"
          },
          {
            "timestamp": "2026-03-02T14:25:00.000Z",
            "value": 49.036106436509655,
            "unit": "Percent"
          },
          {
            "timestamp": "2026-03-02T14:26:00.000Z",
            "value": 48.19618564950653,
            "unit": "Percent"
          },
          {
            "timestamp": "2026-03-02T14:27:00.000Z",
            "value": 45.93936969818176,
            "unit": "Percent"
          },
          {
            "timestamp": "2026-03-02T14:28:00.000Z",
            "value": 44.90159809361929,
            "unit": "Percent"
          },
          {
            "timestamp": "2026-03-02T14:29:00.000Z",
            "value": 45.3628023352794,
            "unit": "Percent"
          }
        ]
      },
      "Maximum": {
        "summary": {
          "min": 7.350612551045922,
          "max": 74.88281315161727,
          "avg": 41.32358728889893,
          "count": 14
        },
        "datapoints": [
          {
            "timestamp": "2026-03-02T14:16:00.000Z",
            "value": 7.350612551045922,
            "unit": "Percent"
          },
          {
            "timestamp": "2026-03-02T14:17:00.000Z",
            "value": 11.341666666666667,
            "unit": "Percent"
          },
          {
            "timestamp": "2026-03-02T14:18:00.000Z",
            "value": 16.35806069898835,
            "unit": "Percent"
          },
          {
            "timestamp": "2026-03-02T14:19:00.000Z",
            "value": 26.716029617770666,
            "unit": "Percent"
          },
          {
            "timestamp": "2026-03-02T14:20:00.000Z",
            "value": 39.56666666666667,
            "unit": "Percent"
          },
          {
            "timestamp": "2026-03-02T14:21:00.000Z",
            "value": 51.60317301603173,
            "unit": "Percent"
          },
          {
            "timestamp": "2026-03-02T14:22:00.000Z",
            "value": 65.2572151814412,
            "unit": "Percent"
          },
          {
            "timestamp": "2026-03-02T14:23:00.000Z",
            "value": 74.88281315161727,
            "unit": "Percent"
          },
          {
            "timestamp": "2026-03-02T14:24:00.000Z",
            "value": 52.017922281259885,
            "unit": "Percent"
          },
          {
            "timestamp": "2026-03-02T14:25:00.000Z",
            "value": 49.036106436509655,
            "unit": "Percent"
          },
          {
            "timestamp": "2026-03-02T14:26:00.000Z",
            "value": 48.19618564950653,
            "unit": "Percent"
          },
          {
            "timestamp": "2026-03-02T14:27:00.000Z",
            "value": 45.93936969818176,
            "unit": "Percent"
          },
          {
            "timestamp": "2026-03-02T14:28:00.000Z",
            "value": 44.90159809361929,
            "unit": "Percent"
          },
          {
            "timestamp": "2026-03-02T14:29:00.000Z",
            "value": 45.3628023352794,
            "unit": "Percent"
          }
        ]
      }
    },
    "DatabaseConnections": {
      "Average": {
        "summary": null,
        "datapoints": [
          {
            "timestamp": "2026-03-02T14:16:00.000Z",
            "unit": "Count"
          },
          {
            "timestamp": "2026-03-02T14:17:00.000Z",
            "unit": "Count"
          },
          {
            "timestamp": "2026-03-02T14:18:00.000Z",
            "unit": "Count"
          },
          {
            "timestamp": "2026-03-02T14:19:00.000Z",
            "unit": "Count"
          },
          {
            "timestamp": "2026-03-02T14:20:00.000Z",
            "unit": "Count"
          },
          {
            "timestamp": "2026-03-02T14:21:00.000Z",
            "unit": "Count"
          },
          {
            "timestamp": "2026-03-02T14:22:00.000Z",
            "unit": "Count"
          },
          {
            "timestamp": "2026-03-02T14:23:00.000Z",
            "unit": "Count"
          },
          {
            "timestamp": "2026-03-02T14:24:00.000Z",
            "unit": "Count"
          },
          {
            "timestamp": "2026-03-02T14:25:00.000Z",
            "unit": "Count"
          },
          {
            "timestamp": "2026-03-02T14:26:00.000Z",
            "unit": "Count"
          },
          {
            "timestamp": "2026-03-02T14:27:00.000Z",
            "unit": "Count"
          },
          {
            "timestamp": "2026-03-02T14:28:00.000Z",
            "unit": "Count"
          },
          {
            "timestamp": "2026-03-02T14:29:00.000Z",
            "unit": "Count"
          }
        ]
      },
      "Maximum": {
        "summary": null,
        "datapoints": [
          {
            "timestamp": "2026-03-02T14:16:00.000Z",
            "unit": "Count"
          },
          {
            "timestamp": "2026-03-02T14:17:00.000Z",
            "unit": "Count"
          },
          {
            "timestamp": "2026-03-02T14:18:00.000Z",
            "unit": "Count"
          },
          {
            "timestamp": "2026-03-02T14:19:00.000Z",
            "unit": "Count"
          },
          {
            "timestamp": "2026-03-02T14:20:00.000Z",
            "unit": "Count"
          },
          {
            "timestamp": "2026-03-02T14:21:00.000Z",
            "unit": "Count"
          },
          {
            "timestamp": "2026-03-02T14:22:00.000Z",
            "unit": "Count"
          },
          {
            "timestamp": "2026-03-02T14:23:00.000Z",
            "unit": "Count"
          },
          {
            "timestamp": "2026-03-02T14:24:00.000Z",
            "unit": "Count"
          },
          {
            "timestamp": "2026-03-02T14:25:00.000Z",
            "unit": "Count"
          },
          {
            "timestamp": "2026-03-02T14:26:00.000Z",
            "unit": "Count"
          },
          {
            "timestamp": "2026-03-02T14:27:00.000Z",
            "unit": "Count"
          },
          {
            "timestamp": "2026-03-02T14:28:00.000Z",
            "unit": "Count"
          },
          {
            "timestamp": "2026-03-02T14:29:00.000Z",
            "unit": "Count"
          }
        ]
      }
    },
    "ReadLatency": {
      "Average": {
        "summary": {
          "min": 0,
          "max": 0.003162393162393162,
          "avg": 0.00022588522588522586,
          "count": 14
        },
        "datapoints": [
          {
            "timestamp": "2026-03-02T14:16:00.000Z",
            "value": 0,
            "unit": "Seconds"
          },
          {
            "timestamp": "2026-03-02T14:17:00.000Z",
            "value": 0,
            "unit": "Seconds"
          },
          {
            "timestamp": "2026-03-02T14:18:00.000Z",
            "value": 0,
            "unit": "Seconds"
          },
          {
            "timestamp": "2026-03-02T14:19:00.000Z",
            "value": 0,
            "unit": "Seconds"
          },
          {
            "timestamp": "2026-03-02T14:20:00.000Z",
            "value": 0,
            "unit": "Seconds"
          },
          {
            "timestamp": "2026-03-02T14:21:00.000Z",
            "value": 0,
            "unit": "Seconds"
          },
          {
            "timestamp": "2026-03-02T14:22:00.000Z",
            "value": 0,
            "unit": "Seconds"
          },
          {
            "timestamp": "2026-03-02T14:23:00.000Z",
            "value": 0,
            "unit": "Seconds"
          },
          {
            "timestamp": "2026-03-02T14:24:00.000Z",
            "value": 0,
            "unit": "Seconds"
          },
          {
            "timestamp": "2026-03-02T14:25:00.000Z",
            "value": 0,
            "unit": "Seconds"
          },
          {
            "timestamp": "2026-03-02T14:26:00.000Z",
            "value": 0,
            "unit": "Seconds"
          },
          {
            "timestamp": "2026-03-02T14:27:00.000Z",
            "value": 0,
            "unit": "Seconds"
          },
          {
            "timestamp": "2026-03-02T14:28:00.000Z",
            "value": 0.003162393162393162,
            "unit": "Seconds"
          },
          {
            "timestamp": "2026-03-02T14:29:00.000Z",
            "value": 0,
            "unit": "Seconds"
          }
        ]
      },
      "Maximum": {
        "summary": {
          "min": 0,
          "max": 0.003162393162393162,
          "avg": 0.00022588522588522586,
          "count": 14
        },
        "datapoints": [
          {
            "timestamp": "2026-03-02T14:16:00.000Z",
            "value": 0,
            "unit": "Seconds"
          },
          {
            "timestamp": "2026-03-02T14:17:00.000Z",
            "value": 0,
            "unit": "Seconds"
          },
          {
            "timestamp": "2026-03-02T14:18:00.000Z",
            "value": 0,
            "unit": "Seconds"
          },
          {
            "timestamp": "2026-03-02T14:19:00.000Z",
            "value": 0,
            "unit": "Seconds"
          },
          {
            "timestamp": "2026-03-02T14:20:00.000Z",
            "value": 0,
            "unit": "Seconds"
          },
          {
            "timestamp": "2026-03-02T14:21:00.000Z",
            "value": 0,
            "unit": "Seconds"
          },
          {
            "timestamp": "2026-03-02T14:22:00.000Z",
            "value": 0,
            "unit": "Seconds"
          },
          {
            "timestamp": "2026-03-02T14:23:00.000Z",
            "value": 0,
            "unit": "Seconds"
          },
          {
            "timestamp": "2026-03-02T14:24:00.000Z",
            "value": 0,
            "unit": "Seconds"
          },
          {
            "timestamp": "2026-03-02T14:25:00.000Z",
            "value": 0,
            "unit": "Seconds"
          },
          {
            "timestamp": "2026-03-02T14:26:00.000Z",
            "value": 0,
            "unit": "Seconds"
          },
          {
            "timestamp": "2026-03-02T14:27:00.000Z",
            "value": 0,
            "unit": "Seconds"
          },
          {
            "timestamp": "2026-03-02T14:28:00.000Z",
            "value": 0.003162393162393162,
            "unit": "Seconds"
          },
          {
            "timestamp": "2026-03-02T14:29:00.000Z",
            "value": 0,
            "unit": "Seconds"
          }
        ]
      }
    },
    "WriteLatency": {
      "Average": {
        "summary": {
          "min": 0.0004031209362808843,
          "max": 0.005745928338762215,
          "avg": 0.0014174898558464214,
          "count": 14
        },
        "datapoints": [
          {
            "timestamp": "2026-03-02T14:16:00.000Z",
            "value": 0.0014285714285714286,
            "unit": "Seconds"
          },
          {
            "timestamp": "2026-03-02T14:17:00.000Z",
            "value": 0.0004093567251461989,
            "unit": "Seconds"
          },
          {
            "timestamp": "2026-03-02T14:18:00.000Z",
            "value": 0.005745928338762215,
            "unit": "Seconds"
          },
          {
            "timestamp": "2026-03-02T14:19:00.000Z",
            "value": 0.0006990014265335235,
            "unit": "Seconds"
          },
          {
            "timestamp": "2026-03-02T14:20:00.000Z",
            "value": 0.0008715596330275229,
            "unit": "Seconds"
          },
          {
            "timestamp": "2026-03-02T14:21:00.000Z",
            "value": 0.0004952510176390773,
            "unit": "Seconds"
          },
          {
            "timestamp": "2026-03-02T14:22:00.000Z",
            "value": 0.0008219988172678888,
            "unit": "Seconds"
          },
          {
            "timestamp": "2026-03-02T14:23:00.000Z",
            "value": 0.0035141354372123603,
            "unit": "Seconds"
          },
          {
            "timestamp": "2026-03-02T14:24:00.000Z",
            "value": 0.0004031209362808843,
            "unit": "Seconds"
          },
          {
            "timestamp": "2026-03-02T14:25:00.000Z",
            "value": 0.0006446540880503145,
            "unit": "Seconds"
          },
          {
            "timestamp": "2026-03-02T14:26:00.000Z",
            "value": 0.000721311475409836,
            "unit": "Seconds"
          },
          {
            "timestamp": "2026-03-02T14:27:00.000Z",
            "value": 0.0009961315280464216,
            "unit": "Seconds"
          },
          {
            "timestamp": "2026-03-02T14:28:00.000Z",
            "value": 0.00231389284020863,
            "unit": "Seconds"
          },
          {
            "timestamp": "2026-03-02T14:29:00.000Z",
            "value": 0.0007799442896935933,
            "unit": "Seconds"
          }
        ]
      },
      "Maximum": {
        "summary": {
          "min": 0.0004031209362808843,
          "max": 0.005745928338762215,
          "avg": 0.0014174898558464214,
          "count": 14
        },
        "datapoints": [
          {
            "timestamp": "2026-03-02T14:16:00.000Z",
            "value": 0.0014285714285714286,
            "unit": "Seconds"
          },
          {
            "timestamp": "2026-03-02T14:17:00.000Z",
            "value": 0.0004093567251461989,
            "unit": "Seconds"
          },
          {
            "timestamp": "2026-03-02T14:18:00.000Z",
            "value": 0.005745928338762215,
            "unit": "Seconds"
          },
          {
            "timestamp": "2026-03-02T14:19:00.000Z",
            "value": 0.0006990014265335235,
            "unit": "Seconds"
          },
          {
            "timestamp": "2026-03-02T14:20:00.000Z",
            "value": 0.0008715596330275229,
            "unit": "Seconds"
          },
          {
            "timestamp": "2026-03-02T14:21:00.000Z",
            "value": 0.0004952510176390773,
            "unit": "Seconds"
          },
          {
            "timestamp": "2026-03-02T14:22:00.000Z",
            "value": 0.0008219988172678888,
            "unit": "Seconds"
          },
          {
            "timestamp": "2026-03-02T14:23:00.000Z",
            "value": 0.0035141354372123603,
            "unit": "Seconds"
          },
          {
            "timestamp": "2026-03-02T14:24:00.000Z",
            "value": 0.0004031209362808843,
            "unit": "Seconds"
          },
          {
            "timestamp": "2026-03-02T14:25:00.000Z",
            "value": 0.0006446540880503145,
            "unit": "Seconds"
          },
          {
            "timestamp": "2026-03-02T14:26:00.000Z",
            "value": 0.000721311475409836,
            "unit": "Seconds"
          },
          {
            "timestamp": "2026-03-02T14:27:00.000Z",
            "value": 0.0009961315280464216,
            "unit": "Seconds"
          },
          {
            "timestamp": "2026-03-02T14:28:00.000Z",
            "value": 0.00231389284020863,
            "unit": "Seconds"
          },
          {
            "timestamp": "2026-03-02T14:29:00.000Z",
            "value": 0.0007799442896935933,
            "unit": "Seconds"
          }
        ]
      }
    },
    "ReadThroughput": {
      "Average": {
        "summary": {
          "min": 0,
          "max": 17062.68537341287,
          "avg": 1555.1319617341858,
          "count": 14
        },
        "datapoints": [
          {
            "timestamp": "2026-03-02T14:16:00.000Z",
            "value": 0,
            "unit": "Bytes/Second"
          },
          {
            "timestamp": "2026-03-02T14:17:00.000Z",
            "value": 1910.2568373363536,
            "unit": "Bytes/Second"
          },
          {
            "timestamp": "2026-03-02T14:18:00.000Z",
            "value": 68.28942980993665,
            "unit": "Bytes/Second"
          },
          {
            "timestamp": "2026-03-02T14:19:00.000Z",
            "value": 68.25187875960209,
            "unit": "Bytes/Second"
          },
          {
            "timestamp": "2026-03-02T14:20:00.000Z",
            "value": 750.4080476999434,
            "unit": "Bytes/Second"
          },
          {
            "timestamp": "2026-03-02T14:21:00.000Z",
            "value": 0,
            "unit": "Bytes/Second"
          },
          {
            "timestamp": "2026-03-02T14:22:00.000Z",
            "value": 0,
            "unit": "Bytes/Second"
          },
          {
            "timestamp": "2026-03-02T14:23:00.000Z",
            "value": 750.0832389958048,
            "unit": "Bytes/Second"
          },
          {
            "timestamp": "2026-03-02T14:24:00.000Z",
            "value": 136.34472313299935,
            "unit": "Bytes/Second"
          },
          {
            "timestamp": "2026-03-02T14:25:00.000Z",
            "value": 684.1718447250618,
            "unit": "Bytes/Second"
          },
          {
            "timestamp": "2026-03-02T14:26:00.000Z",
            "value": 0,
            "unit": "Bytes/Second"
          },
          {
            "timestamp": "2026-03-02T14:27:00.000Z",
            "value": 0,
            "unit": "Bytes/Second"
          },
          {
            "timestamp": "2026-03-02T14:28:00.000Z",
            "value": 17062.68537341287,
            "unit": "Bytes/Second"
          },
          {
            "timestamp": "2026-03-02T14:29:00.000Z",
            "value": 341.3560904060271,
            "unit": "Bytes/Second"
          }
        ]
      }
    },
    "WriteThroughput": {
      "Average": {
        "summary": {
          "min": 956.4666244120492,
          "max": 2497436.2389292135,
          "avg": 623153.083077444,
          "count": 14
        },
        "datapoints": [
          {
            "timestamp": "2026-03-02T14:16:00.000Z",
            "value": 956.4666244120492,
            "unit": "Bytes/Second"
          },
          {
            "timestamp": "2026-03-02T14:17:00.000Z",
            "value": 22923.082048036245,
            "unit": "Bytes/Second"
          },
          {
            "timestamp": "2026-03-02T14:18:00.000Z",
            "value": 2309480.2267422476,
            "unit": "Bytes/Second"
          },
          {
            "timestamp": "2026-03-02T14:19:00.000Z",
            "value": 93027.31074933764,
            "unit": "Bytes/Second"
          },
          {
            "timestamp": "2026-03-02T14:20:00.000Z",
            "value": 142782.18580327104,
            "unit": "Bytes/Second"
          },
          {
            "timestamp": "2026-03-02T14:21:00.000Z",
            "value": 196608.5463245469,
            "unit": "Bytes/Second"
          },
          {
            "timestamp": "2026-03-02T14:22:00.000Z",
            "value": 233576.82939037005,
            "unit": "Bytes/Second"
          },
          {
            "timestamp": "2026-03-02T14:23:00.000Z",
            "value": 2497436.2389292135,
            "unit": "Bytes/Second"
          },
          {
            "timestamp": "2026-03-02T14:24:00.000Z",
            "value": 235535.50921225638,
            "unit": "Bytes/Second"
          },
          {
            "timestamp": "2026-03-02T14:25:00.000Z",
            "value": 169332.53156945278,
            "unit": "Bytes/Second"
          },
          {
            "timestamp": "2026-03-02T14:26:00.000Z",
            "value": 161158.79814021697,
            "unit": "Bytes/Second"
          },
          {
            "timestamp": "2026-03-02T14:27:00.000Z",
            "value": 138113.46429643466,
            "unit": "Bytes/Second"
          },
          {
            "timestamp": "2026-03-02T14:28:00.000Z",
            "value": 2355469.5904289,
            "unit": "Bytes/Second"
          },
          {
            "timestamp": "2026-03-02T14:29:00.000Z",
            "value": 167742.3828255217,
            "unit": "Bytes/Second"
          }
        ]
      }
    },
    "ReadIOPS": {
      "Average": {
        "summary": {
          "min": 0,
          "max": 1.316030585217145,
          "avg": 0.2870231408192549,
          "count": 14
        },
        "datapoints": [
          {
            "timestamp": "2026-03-02T14:16:00.000Z",
            "value": 0,
            "unit": "Count/Second"
          },
          {
            "timestamp": "2026-03-02T14:17:00.000Z",
            "value": 0.16656117792065026,
            "unit": "Count/Second"
          },
          {
            "timestamp": "2026-03-02T14:18:00.000Z",
            "value": 0.016671946116270153,
            "unit": "Count/Second"
          },
          {
            "timestamp": "2026-03-02T14:19:00.000Z",
            "value": 0.016659447572718488,
            "unit": "Count/Second"
          },
          {
            "timestamp": "2026-03-02T14:20:00.000Z",
            "value": 1.316030585217145,
            "unit": "Count/Second"
          },
          {
            "timestamp": "2026-03-02T14:21:00.000Z",
            "value": 0,
            "unit": "Count/Second"
          },
          {
            "timestamp": "2026-03-02T14:22:00.000Z",
            "value": 0,
            "unit": "Count/Second"
          },
          {
            "timestamp": "2026-03-02T14:23:00.000Z",
            "value": 0.18313188825625146,
            "unit": "Count/Second"
          },
          {
            "timestamp": "2026-03-02T14:24:00.000Z",
            "value": 0.03328728592114242,
            "unit": "Count/Second"
          },
          {
            "timestamp": "2026-03-02T14:25:00.000Z",
            "value": 1.3028663058729204,
            "unit": "Count/Second"
          },
          {
            "timestamp": "2026-03-02T14:26:00.000Z",
            "value": 0,
            "unit": "Count/Second"
          },
          {
            "timestamp": "2026-03-02T14:27:00.000Z",
            "value": 0,
            "unit": "Count/Second"
          },
          {
            "timestamp": "2026-03-02T14:28:00.000Z",
            "value": 0.899775056235941,
            "unit": "Count/Second"
          },
          {
            "timestamp": "2026-03-02T14:29:00.000Z",
            "value": 0.08334027835652971,
            "unit": "Count/Second"
          }
        ]
      }
    },
    "WriteIOPS": {
      "Average": {
        "summary": {
          "min": 0.1667973245709139,
          "max": 47.6642360070589,
          "avg": 19.205944365557908,
          "count": 14
        },
        "datapoints": [
          {
            "timestamp": "2026-03-02T14:16:00.000Z",
            "value": 0.1667973245709139,
            "unit": "Count/Second"
          },
          {
            "timestamp": "2026-03-02T14:17:00.000Z",
            "value": 2.2485759019287785,
            "unit": "Count/Second"
          },
          {
            "timestamp": "2026-03-02T14:18:00.000Z",
            "value": 24.04094629966156,
            "unit": "Count/Second"
          },
          {
            "timestamp": "2026-03-02T14:19:00.000Z",
            "value": 10.378835837803619,
            "unit": "Count/Second"
          },
          {
            "timestamp": "2026-03-02T14:20:00.000Z",
            "value": 15.559146412567259,
            "unit": "Count/Second"
          },
          {
            "timestamp": "2026-03-02T14:21:00.000Z",
            "value": 21.391176764813764,
            "unit": "Count/Second"
          },
          {
            "timestamp": "2026-03-02T14:22:00.000Z",
            "value": 24.974558315677083,
            "unit": "Count/Second"
          },
          {
            "timestamp": "2026-03-02T14:23:00.000Z",
            "value": 47.6642360070589,
            "unit": "Count/Second"
          },
          {
            "timestamp": "2026-03-02T14:24:00.000Z",
            "value": 22.801790855982556,
            "unit": "Count/Second"
          },
          {
            "timestamp": "2026-03-02T14:25:00.000Z",
            "value": 18.323645353110177,
            "unit": "Count/Second"
          },
          {
            "timestamp": "2026-03-02T14:26:00.000Z",
            "value": 17.348265173482652,
            "unit": "Count/Second"
          },
          {
            "timestamp": "2026-03-02T14:27:00.000Z",
            "value": 15.542140546309575,
            "unit": "Count/Second"
          },
          {
            "timestamp": "2026-03-02T14:28:00.000Z",
            "value": 32.79180204948763,
            "unit": "Count/Second"
          },
          {
            "timestamp": "2026-03-02T14:29:00.000Z",
            "value": 15.65130427535628,
            "unit": "Count/Second"
          }
        ]
      }
    }
  },
  "files": {
    "k6Summary": "/Users/jromero/dev/src/tech-writing/java25-uprade-tests/runs/Scenarios/REST/read-heavy/java17/2026-02-27/1/k6-summary.txt"
  },
  "generatedAt": "2026-03-02T15:05:04.248Z"
}